lightrun/__init__.py
lightrun/__main__.py
lightrun/appengine_pretty_printers.py
lightrun/backoff.py
lightrun/breakpoints_manager.py
lightrun/capture_collector.py
lightrun/cdbg_native.cpython-39-x86_64-linux-gnu.so
lightrun/connection_manager.py
lightrun/data_visibility_manager.py
lightrun/decorators.py
lightrun/environment_metadata.py
lightrun/hub_client.py
lightrun/imphook.py
lightrun/lightrun_config.py
lightrun/lightrun_native.py
lightrun/log_collector.py
lightrun/log_colored_format.py
lightrun/messages.py
lightrun/module_explorer.py
lightrun/module_search.py
lightrun/module_utils.py
lightrun/piping_manager.py
lightrun/python_breakpoint.py
lightrun/utils.py
lightrun/version.txt
lightrun/version_retriever.py
pytransform/__init__.py
pytransform/_pytransform.so
lightrun-1.76.0.dist-info/METADATA
lightrun-1.76.0.dist-info/WHEEL
lightrun-1.76.0.dist-info/top_level.txt
lightrun-1.76.0.dist-info/RECORD
