Metadata-Version: 2.1
Name: lightrun
Version: 1.76.0
Summary: Add logs and snapshots (virtual breakpoints) to live applications - without stopping them.
Home-page: UNKNOWN
License: Apache License, Version 2.0
Keywords: Lightrun
Platform: UNKNOWN
Classifier: Programming Language :: Python :: 3.9
Classifier: Programming Language :: Python :: 3.10
Classifier: Programming Language :: Python :: 3.11
Classifier: Intended Audience :: Developers
Requires-Dist: httplib2<=0.20.4,>=0.19.1
Requires-Dist: cryptography>=2.1.0
Requires-Dist: psutil>=5.5.1
Requires-Dist: pyyaml>=3.13
Requires-Dist: google-re2==1.0
